[
  {
    "rank": "96",
    "brand": "콜드웜",
    "product_name": "waffle warmer hoodie (cream color)",
    "discount": "20%",
    "price": "59,900원",
    "image_file": "rank_096.jpg",
    "image_url": "https://image.msscdn.net/thumbnails/images/goods_img/20250915/5463193/5463193_17664699922938_500.jpg?w=780"
  },
  {
    "rank": "97",
    "brand": "무신사 스탠다드",
    "product_name": "스웨트셔츠 2팩",
    "discount": "50%",
    "price": "29,990원",
    "image_file": "rank_097.jpg",
    "image_url": "https://image.msscdn.net/thumbnails/images/goods_img/20251022/5629414/5629414_17630280006505_500.jpg?w=780"
  },
  {
    "rank": "98",
    "brand": "루나키후",
    "product_name": "WXJ023 리에 네코 레이스 엄청난 기모 후드집업 (BROWN)",
    "discount": "30%",
    "price": "83,300원",
    "image_file": "rank_098.jpg",
    "image_url": "https://image.msscdn.net/thumbnails/images/goods_img/20250929/5544770/5544770_17600597832315_500.jpg?w=780"
  },
  {
    "rank": "99",
    "brand": "언탭트 스튜디오",
    "product_name": "2WAY 비건 스웨이드 블루종 자켓 3Color",
    "discount": "40%",
    "price": "48,720원",
    "image_file": "rank_099.jpg",
    "image_url": "https://image.msscdn.net/thumbnails/images/goods_img/20250811/5311114/5311114_17570503866331_500.jpg?w=780"
  },
  {
    "rank": "100",
    "brand": "이알티알",
    "product_name": "Emanate Logo Jogger Pants Melange Grey",
    "discount": "20%",
    "price": "78,400원",
    "image_file": "rank_100.png",
    "image_url": "https://image.msscdn.net/thumbnails/images/goods_img/20250923/5513539/5513539_17586048906322_500.png?w=780"
  },
  {
    "rank": "101",
    "brand": "드로우핏",
    "product_name": "밴스 레더 크로스 토트백 [BLACK]",
    "discount": "10%",
    "price": "66,600원",
    "image_file": "rank_101.jpg",
    "image_url": "https://image.msscdn.net/thumbnails/images/goods_img/20250901/5385028/5385028_17567144801930_500.jpg?w=780"
  },
  {
    "rank": "102",
    "brand": "더 드리머",
    "product_name": "중량담요 후드티 - 5COL",
    "discount": "30%",
    "price": "66,500원",
    "image_file": "rank_102.jpg",
    "image_url": "https://image.msscdn.net/thumbnails/images/goods_img/20251029/5658631/5658631_17684579793207_500.jpg?w=780"
  },
  {
    "rank": "103",
    "brand": "칙스",
    "product_name": "커브라인 후디드 라이트 패딩 (2colors)",
    "discount": "58%",
    "price": "35,910원",
    "image_file": "rank_103.jpg",
    "image_url": "https://image.msscdn.net/thumbnails/images/goods_img/20250929/5541815/5541815_17630972241762_500.jpg?w=780"
  },
  {
    "rank": "104",
    "brand": "무신사 스탠다드",
    "product_name": "시티 레저 시어 립스탑 후디드 라이트 다운 재킷 [라이트 그레이]",
    "discount": "10%",
    "price": "116,990원",
    "image_file": "rank_104.jpg",
    "image_url": "https://image.msscdn.net/thumbnails/images/goods_img/20250701/5215534/5215534_17610119106335_500.jpg?w=780"
  },
  {
    "rank": "105",
    "brand": "수아레 우먼",
    "product_name": "(우먼)라이트 시어쉘 패딩 점퍼 - 3 COLOR",
    "discount": "33%",
    "price": "109,900원",
    "image_file": "rank_105.jpg",
    "image_url": "https://image.msscdn.net/thumbnails/images/goods_img/20250930/5550560/5550560_17593152299893_500.jpg?w=780"
  },
  {
    "rank": "106",
    "brand": "이소",
    "product_name": "에투 타우페",
    "discount": "33%",
    "price": "92,460원",
    "image_file": "rank_106.jpg",
    "image_url": "https://image.msscdn.net/thumbnails/images/goods_img/20251016/5603776/5603776_17618110191560_500.jpg?w=780"
  },
  {
    "rank": "107",
    "brand": "티엔지티",
    "product_name": "European-goose Corduroy Down Jumper (Dark Navy) TNJU5F206N2",
    "discount": "28%",
    "price": "208,080원",
    "image_file": "rank_107.jpg",
    "image_url": "https://image.msscdn.net/thumbnails/images/goods_img/20250926/5536247/5536247_17588600667760_500.jpg?w=780"
  },
  {
    "rank": "108",
    "brand": "언탭트 스튜디오",
    "product_name": "오버핏 2WAY 아란 케이블 라운드 집업 니트 가디건 5Color",
    "discount": "30%",
    "price": "37,800원",
    "image_file": "rank_108.jpg",
    "image_url": "https://image.msscdn.net/thumbnails/images/goods_img/20250812/5311331/5311331_17555824831747_500.jpg?w=780"
  },
  {
    "rank": "109",
    "brand": "트릴리온",
    "product_name": "라이트 후디 패딩 자켓_그레이",
    "discount": "37%",
    "price": "45,990원",
    "image_file": "rank_109.jpg",
    "image_url": "https://image.msscdn.net/thumbnails/images/goods_img/20250910/5438735/5438735_17575615961166_500.jpg?w=780"
  },
  {
    "rank": "110",
    "brand": "씨타",
    "product_name": "Signature Logo Knit Hair Band_CTA929(4color)",
    "discount": "10%",
    "price": "34,200원",
    "image_file": "rank_110.jpg",
    "image_url": "https://image.msscdn.net/thumbnails/images/goods_img/20250819/5340034/5340034_17676827936652_500.jpg?w=780"
  },
  {
    "rank": "111",
    "brand": "나이키",
    "product_name": "에어 맥스 모토 2K M - 블랙:메탈릭 다크 그레이:다크 스모크 그레이 / IO9279-001",
    "discount": "",
    "price": "149,000원",
    "image_file": "rank_111.jpg",
    "image_url": "https://image.msscdn.net/thumbnails/images/goods_img/20251014/5590698/5590698_17606688450667_500.jpg?w=780"
  },
  {
    "rank": "112",
    "brand": "나이키",
    "product_name": "에어 포스 1 07 M - 세일 / IH1698-001",
    "discount": "",
    "price": "149,000원",
    "image_file": "rank_112.jpg",
    "image_url": "https://image.msscdn.net/thumbnails/images/goods_img/20251209/5816830/5816830_17682702141955_500.jpg?w=780"
  },
  {
    "rank": "113",
    "brand": "브라운브레스",
    "product_name": "TIGER CAMO TAG HOODIE - BLACK",
    "discount": "10%",
    "price": "89,100원",
    "image_file": "rank_113.jpg",
    "image_url": "https://image.msscdn.net/thumbnails/images/goods_img/20260108/5878500/5878500_17683764955073_500.jpg?w=780"
  },
  {
    "rank": "114",
    "brand": "스탠드오일",
    "product_name": "Breezy Bag · 브리지백",
    "discount": "",
    "price": "149,000원",
    "image_file": "rank_114.jpg",
    "image_url": "https://image.msscdn.net/thumbnails/images/goods_img/20250808/5303152/5303152_17687872770771_500.jpg?w=780"
  },
  {
    "rank": "115",
    "brand": "드로우핏",
    "product_name": "[패션플래닛X드로우핏] 워시드 크롭 옥스퍼드 셔츠 [5color]",
    "discount": "10%",
    "price": "49,500원",
    "image_file": "rank_115.jpg",
    "image_url": "https://image.msscdn.net/thumbnails/images/goods_img/20250728/5275916/5275916_17564335238263_500.jpg?w=780"
  },
  {
    "rank": "116",
    "brand": "꼼파뇨",
    "product_name": "캣 스티치 레글런 피그먼트 맨투맨 고스트그레이",
    "discount": "66%",
    "price": "25,690원",
    "image_file": "rank_116.jpg",
    "image_url": "https://image.msscdn.net/thumbnails/images/goods_img/20250930/5555157/5555157_17592806978863_500.jpg?w=780"
  },
  {
    "rank": "117",
    "brand": "론론",
    "product_name": "PATCH ROLL UP DENIM PANTS RED CHECK",
    "discount": "44%",
    "price": "61,600원",
    "image_file": "rank_117.jpg",
    "image_url": "https://image.msscdn.net/thumbnails/images/goods_img/20251027/5649111/5649111_17663831102512_500.jpg?w=780"
  },
  {
    "rank": "118",
    "brand": "뎁스",
    "product_name": "니트 슬리브 트러커 집업 (블랙)",
    "discount": "",
    "price": "219,000원",
    "image_file": "rank_118.jpg",
    "image_url": "https://image.msscdn.net/thumbnails/images/goods_img/20250916/5464810/5464810_17687936235000_500.jpg?w=780"
  },
  {
    "rank": "119",
    "brand": "코오롱스포츠",
    "product_name": "여성 쿠치 윈드스토퍼 중기장 미드 다운 TVJDW25612BLK",
    "discount": "17%",
    "price": "430,000원",
    "image_file": "rank_119.jpg",
    "image_url": "https://image.msscdn.net/thumbnails/images/goods_img/20251016/5604129/5604129_17671569014065_500.jpg?w=780"
  },
  {
    "rank": "120",
    "brand": "아웃스탠딩",
    "product_name": "MA-1 FLIGHT JACKET(WOOL INSULATION)_SAGE GREEN",
    "discount": "20%",
    "price": "211,200원",
    "image_file": "rank_120.jpg",
    "image_url": "https://image.msscdn.net/thumbnails/images/goods_img/20250911/5441759/5441759_17649141948186_500.jpg?w=780"
  },
  {
    "rank": "121",
    "brand": "나이키",
    "product_name": "ACG 라바 플로우 써마 핏 ADV 팬츠 M - 블랙:서밋 화이트 / HV4462-010",
    "discount": "30%",
    "price": "209,300원",
    "image_file": "rank_121.jpg",
    "image_url": "https://image.msscdn.net/thumbnails/images/goods_img/20251023/5634576/5634576_17615439544454_500.jpg?w=780"
  },
  {
    "rank": "122",
    "brand": "스튜디오 톰보이",
    "product_name": "[MEN] 캐멀블렌디드 더블 코트_챠콜 9155411307",
    "discount": "40%",
    "price": "419,400원",
    "image_file": "rank_122.jpg",
    "image_url": "https://image.msscdn.net/thumbnails/images/goods_img/20251111/5711390/5711390_17628213539376_500.jpg?w=780"
  },
  {
    "rank": "123",
    "brand": "노스페이스",
    "product_name": "NJ1DR95A 여성 1996 레트로 눕시 자켓 BLACK",
    "discount": "5%",
    "price": "398,050원",
    "image_file": "rank_123.jpg",
    "image_url": "https://image.msscdn.net/thumbnails/images/goods_img/20250825/5357325/5357325_17560867013717_500.jpg?w=780"
  },
  {
    "rank": "124",
    "brand": "뉴발란스",
    "product_name": "NBPFGS103M / 1080 V15 (남성, 2E) (L/GRAY)",
    "discount": "",
    "price": "209,000원",
    "image_file": "rank_124.jpg",
    "image_url": "https://image.msscdn.net/thumbnails/images/goods_img/20260107/5873292/5873292_17677510780115_500.jpg?w=780"
  },
  {
    "rank": "125",
    "brand": "에프씨엠엠 스포츠",
    "product_name": "바라클라바 플리스 풀오버 후디 3color",
    "discount": "37%",
    "price": "62,370원",
    "image_file": "rank_125.jpg",
    "image_url": "https://image.msscdn.net/thumbnails/images/goods_img/20250911/5443207/5443207_17582600800124_500.jpg?w=780"
  },
  {
    "rank": "126",
    "brand": "디스커버리 익스페디션",
    "product_name": "여성 반슬리 다운 크롭 숏패딩 (BLACK)",
    "discount": "30%",
    "price": "209,300원",
    "image_file": "rank_126.jpg",
    "image_url": "https://image.msscdn.net/thumbnails/images/goods_img/20251013/5580856/5580856_17657642982990_500.jpg?w=780"
  },
  {
    "rank": "127",
    "brand": "브랜디드",
    "product_name": "[SUPERIOR] CLOUD SUPERFINE V-NECK KNIT [CHARCOAL]",
    "discount": "30%",
    "price": "89,600원",
    "image_file": "rank_127.jpg",
    "image_url": "https://image.msscdn.net/thumbnails/images/goods_img/20251118/5745851/5745851_17645536387702_500.jpg?w=780"
  },
  {
    "rank": "128",
    "brand": "르아브",
    "product_name": "모노샤인 파라수트 트랙 팬츠 블랙",
    "discount": "33%",
    "price": "76,480원",
    "image_file": "rank_128.jpg",
    "image_url": "https://image.msscdn.net/thumbnails/images/goods_img/20250904/5405163/5405163_17570658030478_500.jpg?w=780"
  },
  {
    "rank": "129",
    "brand": "마리떼 프랑소와 저버",
    "product_name": "GLOSSY DOWN JACKET black",
    "discount": "50%",
    "price": "134,500원",
    "image_file": "rank_129.jpg",
    "image_url": "https://image.msscdn.net/thumbnails/images/goods_img/20250918/5488913/5488913_17610195567287_500.jpg?w=780"
  },
  {
    "rank": "130",
    "brand": "언탭트 스튜디오",
    "product_name": "워시드 오버 와이드 코튼 데님팬츠 3Color",
    "discount": "40%",
    "price": "31,620원",
    "image_file": "rank_130.jpg",
    "image_url": "https://image.msscdn.net/thumbnails/images/goods_img/20250812/5311382/5311382_17549965010305_500.jpg?w=780"
  },
  {
    "rank": "131",
    "brand": "디퍼슈",
    "product_name": "쿠바 스니커즈 7CM [올블랙 데님]",
    "discount": "30%",
    "price": "99,800원",
    "image_file": "rank_131.png",
    "image_url": "https://image.msscdn.net/thumbnails/images/goods_img/20251222/5845071/5845071_17663752265096_500.png?w=780"
  },
  {
    "rank": "132",
    "brand": "노스페이스",
    "product_name": "NJ1DS00A 마테호른 다운 자켓 BLACK",
    "discount": "5%",
    "price": "379,050원",
    "image_file": "rank_132.jpg",
    "image_url": "https://image.msscdn.net/thumbnails/images/goods_img/20250923/5514397/5514397_17586076104556_500.jpg?w=780"
  },
  {
    "rank": "133",
    "brand": "르아르",
    "product_name": "에센셜 후디드 라이트 패딩 자켓 [차콜]",
    "discount": "60%",
    "price": "56,800원",
    "image_file": "rank_133.jpg",
    "image_url": "https://image.msscdn.net/thumbnails/images/goods_img/20250909/5425135/5425135_17609249899063_500.jpg?w=780"
  },
  {
    "rank": "134",
    "brand": "엘씨디씨티엠",
    "product_name": "LAYERED CHECK SWEATPANTS (CLASSIC BLACK)",
    "discount": "19%",
    "price": "136,890원",
    "image_file": "rank_134.jpg",
    "image_url": "https://image.msscdn.net/thumbnails/images/goods_img/20250807/5302552/5302552_17545624377883_500.jpg?w=780"
  },
  {
    "rank": "135",
    "brand": "디미트리블랙",
    "product_name": "바라클라바 슬래쉬 후드 집업_쉐르파 플리스 차콜",
    "discount": "18%",
    "price": "42,900원",
    "image_file": "rank_135.jpg",
    "image_url": "https://image.msscdn.net/thumbnails/images/goods_img/20250917/5477159/5477159_17581840830008_500.jpg?w=780"
  },
  {
    "rank": "136",
    "brand": "젝시믹스",
    "product_name": "[2PACK] V업 3D 플러스 레깅스 XP9156T",
    "discount": "64%",
    "price": "27,840원",
    "image_file": "rank_136.jpg",
    "image_url": "https://image.msscdn.net/thumbnails/images/goods_img/20251208/5811545/5811545_17688058340524_500.jpg?w=780"
  },
  {
    "rank": "137",
    "brand": "언타이틀 서울",
    "product_name": "언타이틀 스테리나잇 스트라이프 후드집업 블랙",
    "discount": "20%",
    "price": "68,800원",
    "image_file": "rank_137.jpg",
    "image_url": "https://image.msscdn.net/thumbnails/images/goods_img/20250722/5264797/5264797_17689759273536_500.jpg?w=780"
  },
  {
    "rank": "138",
    "brand": "스타벅스",
    "product_name": "스타벅스 사이렌 핸들 글라스 500ml(2P)",
    "discount": "5%",
    "price": "19,000원",
    "image_file": "rank_138.jpg",
    "image_url": "https://image.msscdn.net/thumbnails/images/goods_img/20251013/5583109/5583109_17612658038520_500.jpg?w=780"
  },
  {
    "rank": "139",
    "brand": "제너럴아이디어",
    "product_name": "UNISEX 소프트 하이넥 플리스 아노락 세트[BROWN] / SBE4U02010",
    "discount": "38%",
    "price": "51,100원",
    "image_file": "rank_139.png",
    "image_url": "https://image.msscdn.net/thumbnails/images/goods_img/20251112/5721999/5721999_17688893463519_500.png?w=780"
  },
  {
    "rank": "140",
    "brand": "락피쉬웨더웨어",
    "product_name": "BLISS LACEUP SNEAKERS V2 - 5 colors",
    "discount": "15%",
    "price": "97,700원",
    "image_file": "rank_140.jpg",
    "image_url": "https://image.msscdn.net/thumbnails/images/goods_img/20250825/5358532/5358532_17573980470268_500.jpg?w=780"
  },
  {
    "rank": "141",
    "brand": "야세",
    "product_name": "젤라비x야세 워싱카우 캡토 롱 부츠 브라운",
    "discount": "5%",
    "price": "378,100원",
    "image_file": "rank_141.png",
    "image_url": "https://image.msscdn.net/thumbnails/images/goods_img/20250922/5507270/5507270_17615640839288_500.png?w=780"
  },
  {
    "rank": "142",
    "brand": "아크테릭스",
    "product_name": "맨티스 1 웨이스트팩 - 24K BLACK / ABPFU09234",
    "discount": "5%",
    "price": "76,000원",
    "image_file": "rank_142.jpg",
    "image_url": "https://image.msscdn.net/thumbnails/images/goods_img/20251218/5839342/5839342_17665589279752_500.jpg?w=780"
  },
  {
    "rank": "143",
    "brand": "디키즈",
    "product_name": "리버서블 헤비 다운 재킷 Black",
    "discount": "50%",
    "price": "124,500원",
    "image_file": "rank_143.jpg",
    "image_url": "https://image.msscdn.net/thumbnails/images/goods_img/20250923/5513438/5513438_17629926745440_500.jpg?w=780"
  },
  {
    "rank": "144",
    "brand": "플레어업",
    "product_name": "Asymmetrical Draped Layered Long Skirt (FL-256_Black)",
    "discount": "10%",
    "price": "125,100원",
    "image_file": "rank_144.jpg",
    "image_url": "https://image.msscdn.net/thumbnails/images/goods_img/20250813/5317074/5317074_17630779437723_500.jpg?w=780"
  },
  {
    "rank": "145",
    "brand": "메인부스",
    "product_name": "[비틀즈] 와플턴 헨리넥 티셔츠(베이지)",
    "discount": "25%",
    "price": "73,900원",
    "image_file": "rank_145.jpg",
    "image_url": "https://image.msscdn.net/thumbnails/images/goods_img/20250820/5342766/5342766_17568663708656_500.jpg?w=780"
  },
  {
    "rank": "146",
    "brand": "제너럴아이디어",
    "product_name": "레이어드 브이넥 니트 풀오버 [MELANGE GREY] / WBE3L05512",
    "discount": "41%",
    "price": "36,400원",
    "image_file": "rank_146.jpg",
    "image_url": "https://image.msscdn.net/thumbnails/images/goods_img/20250819/5336051/5336051_17555737510190_500.jpg?w=780"
  },
  {
    "rank": "147",
    "brand": "몽벨",
    "product_name": "US 플라즈마 1000 다운 자켓 남성 - LTSV / JBWIWMDL062",
    "discount": "",
    "price": "369,000원",
    "image_file": "rank_147.jpg",
    "image_url": "https://image.msscdn.net/thumbnails/images/goods_img/20251031/5673051/5673051_17618967265223_500.jpg?w=780"
  },
  {
    "rank": "148",
    "brand": "트리밍버드",
    "product_name": "Vintage Washed Leather Jacket [ Navy ]",
    "discount": "30%",
    "price": "258,300원",
    "image_file": "rank_148.jpg",
    "image_url": "https://image.msscdn.net/thumbnails/images/goods_img/20250902/5393686/5393686_17568183980688_500.jpg?w=780"
  },
  {
    "rank": "149",
    "brand": "탄산마그네슘",
    "product_name": "오디피기X탄산 와플 버튼 후드티 (레몬)",
    "discount": "33%",
    "price": "85,790원",
    "image_file": "rank_149.jpg",
    "image_url": "https://image.msscdn.net/thumbnails/images/goods_img/20251209/5817212/5817212_17667175027537_500.jpg?w=780"
  }
]